typedjsonrpc/__init__.py
typedjsonrpc/_version.py
typedjsonrpc/errors.py
typedjsonrpc/method_info.py
typedjsonrpc/parameter_checker.py
typedjsonrpc/registry.py
typedjsonrpc/server.py
typedjsonrpc-0.4.0.dist-info/DESCRIPTION.rst
typedjsonrpc-0.4.0.dist-info/METADATA
typedjsonrpc-0.4.0.dist-info/RECORD
typedjsonrpc-0.4.0.dist-info/WHEEL
typedjsonrpc-0.4.0.dist-info/metadata.json
typedjsonrpc-0.4.0.dist-info/top_level.txt
