Metadata-Version: 2.0
Name: typedjsonrpc
Version: 0.4.0
Summary: A typed decorator-based JSON-RPC library for Python
Home-page: https://github.com/palantir/typedjsonrpc
Author: Michael Nazario
Author-email: mnazario@palantir.com
License: Apache License 2.0
Keywords: jsonrpc json-rpc rpc
Platform: UNKNOWN
Classifier: Development Status :: 4 - Beta
Classifier: Operating System :: OS Independent
Classifier: Intended Audience :: Developers
Classifier: Topic :: Internet :: WWW/HTTP :: WSGI :: Application
Classifier: License :: OSI Approved :: Apache Software License
Classifier: Programming Language :: Python
Classifier: Programming Language :: Python :: 2
Classifier: Programming Language :: Python :: 2.7
Classifier: Programming Language :: Python :: 3
Classifier: Programming Language :: Python :: 3.4
Requires-Dist: six (>=1.0.0,<2.0.0)
Requires-Dist: werkzeug (>=0.10.0,<0.11.0)
Requires-Dist: wrapt (>=1.10.0,<2.0.0)
